news_client/__init__.py
news_client/news_consumer.py
aij_news_client-1.0.10.dist-info/LICENSE.txt
aij_news_client-1.0.10.dist-info/METADATA
aij_news_client-1.0.10.dist-info/WHEEL
aij_news_client-1.0.10.dist-info/entry_points.txt
aij_news_client-1.0.10.dist-info/top_level.txt
aij_news_client-1.0.10.dist-info/RECORD
