Metadata-Version: 2.1
Name: aij-news-client
Version: 1.0.10
Summary: AI Journalist News Client package
Author-email: Yilmaz Mustafa <dev@mail.be>
License: Copyright (c) 2016 The Python Packaging Authority (PyPA)
Project-URL: Homepage, https://www.codesapien.be/aij/
Project-URL: Bug Reports, https://github.com/codesapienbe/aij-news-client/issues
Project-URL: Funding, https://donate.pypi.org
Project-URL: Say Thanks!, http://saythanks.io/to/aij
Project-URL: Source, https://github.com/codesapienbe/aij-news-client
Keywords: aij,setuptools,development
Classifier: Development Status :: 3 - Alpha
Classifier: Intended Audience :: Developers
Classifier: Topic :: Software Development :: Build Tools
Classifier: License :: OSI Approved :: MIT License
Classifier: Programming Language :: Python :: 3
Classifier: Programming Language :: Python :: 3.7
Classifier: Programming Language :: Python :: 3.8
Classifier: Programming Language :: Python :: 3.9
Classifier: Programming Language :: Python :: 3.10
Classifier: Programming Language :: Python :: 3.11
Classifier: Programming Language :: Python :: 3 :: Only
Requires-Python: >=3.7
License-File: LICENSE.txt
Requires-Dist: peppercorn
Requires-Dist: opencv-python
Requires-Dist: mediapipe
Requires-Dist: screeninfo
Requires-Dist: cvzone
Requires-Dist: pika
Provides-Extra: dev
Requires-Dist: check-manifest ; extra == 'dev'
Provides-Extra: test
Requires-Dist: coverage ; extra == 'test'
